ycb_utils/__init__.py
ycb_utils/stl_files/002_master_chef_can.stl
ycb_utils/stl_files/003_cracker_box.stl
ycb_utils/stl_files/004_sugar_box.stl
ycb_utils/stl_files/005_tomato_soup_can.stl
ycb_utils/stl_files/006_mustard_bottle.stl
ycb_utils/stl_files/007_tuna_fish_can.stl
ycb_utils/stl_files/008_pudding_box.stl
ycb_utils/stl_files/009_gelatin_box.stl
ycb_utils/stl_files/010_potted_meat_can.stl
ycb_utils/stl_files/011_banana.stl
ycb_utils/stl_files/012_strawberry.stl
ycb_utils/stl_files/013_apple.stl
ycb_utils/stl_files/014_lemon.stl
ycb_utils/stl_files/015_peach.stl
ycb_utils/stl_files/016_pear.stl
ycb_utils/stl_files/017_orange.stl
ycb_utils/stl_files/018_plum.stl
ycb_utils/stl_files/019_pitcher_base.stl
ycb_utils/stl_files/021_bleach_cleanser.stl
ycb_utils/stl_files/022_windex_bottle.stl
ycb_utils/stl_files/024_bowl.stl
ycb_utils/stl_files/025_mug.stl
ycb_utils/stl_files/026_sponge.stl
ycb_utils/stl_files/028_skillet_lid.stl
ycb_utils/stl_files/029_plate.stl
ycb_utils/stl_files/030_fork.stl
ycb_utils/stl_files/031_spoon.stl
ycb_utils/stl_files/032_knife.stl
ycb_utils/stl_files/033_spatula.stl
ycb_utils/stl_files/035_power_drill.stl
ycb_utils/stl_files/036_wood_block.stl
ycb_utils/stl_files/037_scissors.stl
ycb_utils/stl_files/038_padlock.stl
ycb_utils/stl_files/040_large_marker.stl
ycb_utils/stl_files/042_adjustable_wrench.stl
ycb_utils/stl_files/043_phillips_screwdriver.stl
ycb_utils/stl_files/044_flat_screwdriver.stl
ycb_utils/stl_files/048_hammer.stl
ycb_utils/stl_files/050_medium_clamp.stl
ycb_utils/stl_files/051_large_clamp.stl
ycb_utils/stl_files/052_extra_large_clamp.stl
ycb_utils/stl_files/053_mini_soccer_ball.stl
ycb_utils/stl_files/054_softball.stl
ycb_utils/stl_files/055_baseball.stl
ycb_utils/stl_files/056_tennis_ball.stl
ycb_utils/stl_files/057_racquetball.stl
ycb_utils/stl_files/058_golf_ball.stl
ycb_utils/stl_files/059_chain.stl
ycb_utils/stl_files/061_foam_brick.stl
ycb_utils/stl_files/062_dice.stl
ycb_utils/stl_files/063-a_marbles.stl
ycb_utils-0.0.2.dist-info/METADATA
ycb_utils-0.0.2.dist-info/WHEEL
ycb_utils-0.0.2.dist-info/top_level.txt
ycb_utils-0.0.2.dist-info/RECORD
