Metadata-Version: 2.1
Name: ycb-utils
Version: 0.0.2
Summary: ycb utils
Author: Hirokazu Ishida
Author-email: h-ishida@jsk.imi.i.u-tokyo.ac.jp
License: MIT
Requires-Dist: trimesh
